[{
  "SourceFile": "old-tree-north-berwick-250807_1234028673_o.jpg",
  "ImageWidth": 3888,
  "ImageHeight": 2592,
  "BitsPerSample": "8 8 8",
  "PhotometricInterpretation": "RGB",
  "Make": "Canon",
  "Model": "Canon EOS 400D DIGITAL",
  "Orientation": "Horizontal (normal)",
  "SamplesPerPixel": 3,
  "XResolution": 594.8333,
  "YResolution": 594.8333,
  "ResolutionUnit": "inches",
  "Software": "Adobe Photoshop Elements 11.0 Windows",
  "ModifyDate": "2017:04:14 14:12:18",
  "Artist": "unknown",
  "YCbCrPositioning": "Co-sited",
  "ExposureTime": "1/500",
  "FNumber": 6.3,
  "ExposureProgram": "Shutter speed priority AE",
  "ISO": 200,
  "ExifVersion": "0221",
  "DateTimeOriginal": "2007:08:25 15:16:42",
  "CreateDate": "2007:08:25 15:16:42",
  "ComponentsConfiguration": "Y, Cb, Cr, -",
  "ShutterSpeedValue": "1/500",
  "ApertureValue": 6.3,
  "ExposureCompensation": 0,
  "MeteringMode": "Multi-segment",
  "Flash": "Off, Did not fire",
  "FocalLength": "86.0 mm",
  "FlashpixVersion": "0100",
  "ColorSpace": "sRGB",
  "ExifImageWidth": 3569,
  "ExifImageHeight": 2379,
  "InteropIndex": "R98 - DCF basic file (sRGB)",
  "InteropVersion": "0100",
  "FocalPlaneXResolution": 4433.295325,
  "FocalPlaneYResolution": 4453.608247,
  "FocalPlaneResolutionUnit": "inches",
  "CustomRendered": "Custom",
  "ExposureMode": "Auto",
  "WhiteBalance": "Auto",
  "SceneCaptureType": "Standard",
  "Padding": "(Binary data 2060 bytes, use -b option to extract)",
  "OffsetSchema": 4148,
  "Compression": "JPEG (old-style)",
  "ThumbnailOffset": 5042,
  "ThumbnailLength": 7531,
  "ThumbnailImage": "(Binary data 7531 bytes, use -b option to extract)"
}]
